helga_meet/__init__.py
helga_meet/helga_meet.py
helga_meet-1.1.1.dist-info/DESCRIPTION.rst
helga_meet-1.1.1.dist-info/METADATA
helga_meet-1.1.1.dist-info/RECORD
helga_meet-1.1.1.dist-info/WHEEL
helga_meet-1.1.1.dist-info/entry_points.txt
helga_meet-1.1.1.dist-info/metadata.json
helga_meet-1.1.1.dist-info/top_level.txt
helga_meet-1.1.1.dist-info/zip-safe
tests/__init__.py
tests/test_meet.py
